octavia_loxilb_driver/README.md
octavia_loxilb_driver/__init__.py
octavia_loxilb_driver/requirements.txt
octavia_loxilb_driver/setup.py
octavia_loxilb_driver/version.py
octavia_loxilb_driver/api/README.md
octavia_loxilb_driver/api/__init__.py
octavia_loxilb_driver/api/loxilb_client.py
octavia_loxilb_driver/cmd/__init__.py
octavia_loxilb_driver/cmd/health_check.py
octavia_loxilb_driver/cmd/loxilb_controller_worker.py
octavia_loxilb_driver/cmd/loxilb_worker.py
octavia_loxilb_driver/cmd/setup.py
octavia_loxilb_driver/common/__init__.py
octavia_loxilb_driver/common/config.py
octavia_loxilb_driver/common/constants.py
octavia_loxilb_driver/common/exceptions.py
octavia_loxilb_driver/common/loxilb_network_config.py
octavia_loxilb_driver/common/network_utils.py
octavia_loxilb_driver/common/openstack_sdk_utils.py
octavia_loxilb_driver/common/state_reconciler.py
octavia_loxilb_driver/common/utils.py
octavia_loxilb_driver/controller/__init__.py
octavia_loxilb_driver/controller/controller_worker.py
octavia_loxilb_driver/controller/queue/__init__.py
octavia_loxilb_driver/controller/queue/consumer.py
octavia_loxilb_driver/controller/queue/endpoints.py
octavia_loxilb_driver/controller/worker/__init__.py
octavia_loxilb_driver/controller/worker/flows/__init__.py
octavia_loxilb_driver/controller/worker/flows/flow_utils.py
octavia_loxilb_driver/controller/worker/flows/healthmonitor_flows.py
octavia_loxilb_driver/controller/worker/flows/l7policy_flows.py
octavia_loxilb_driver/controller/worker/flows/l7rule_flows.py
octavia_loxilb_driver/controller/worker/flows/listener_flows.py
octavia_loxilb_driver/controller/worker/flows/loadbalancer_flows.py
octavia_loxilb_driver/controller/worker/flows/loxilb_flows.py
octavia_loxilb_driver/controller/worker/flows/loxilb_load_balancer_flows.py
octavia_loxilb_driver/controller/worker/flows/member_flows.py
octavia_loxilb_driver/controller/worker/flows/pool_flows.py
octavia_loxilb_driver/controller/worker/tasks/__init__.py
octavia_loxilb_driver-1.0.3.dist-info/licenses/LICENSE
octavia_loxilb_driver-1.0.3.dist-info/METADATA
octavia_loxilb_driver-1.0.3.dist-info/WHEEL
octavia_loxilb_driver-1.0.3.dist-info/entry_points.txt
octavia_loxilb_driver-1.0.3.dist-info/top_level.txt
octavia_loxilb_driver-1.0.3.dist-info/RECORD
