Metadata-Version: 2.4
Name: octavia-loxilb-driver
Version: 1.0.3
Summary: LoxiLB provider driver for OpenStack Octavia Load Balancer as a Service
Author-email: OpenStack Community <openstack-discuss@lists.openstack.org>
Maintainer-email: OpenStack Community <openstack-discuss@lists.openstack.org>
License-Expression: Apache-2.0
Project-URL: Homepage, https://github.com/NLX-SeokHwanKong/octavia-loxilb-driver
Project-URL: Documentation, https://github.com/NLX-SeokHwanKong/octavia-loxilb-driver#readme
Project-URL: Repository, https://github.com/NLX-SeokHwanKong/octavia-loxilb-driver.git
Project-URL: Bug Reports, https://github.com/NLX-SeokHwanKong/octavia-loxilb-driver/issues
Project-URL: Changelog, https://github.com/NLX-SeokHwanKong/octavia-loxilb-driver/blob/main/CHANGELOG.md
Keywords: openstack,octavia,loadbalancer,loxilb
Classifier: Development Status :: 4 - Beta
Classifier: Environment :: OpenStack
Classifier: Intended Audience :: System Administrators
Classifier: Operating System :: POSIX :: Linux
Classifier: Programming Language :: Python :: 3
Classifier: Programming Language :: Python :: 3.8
Classifier: Programming Language :: Python :: 3.9
Classifier: Programming Language :: Python :: 3.10
Classifier: Programming Language :: Python :: 3.11
Classifier: Topic :: System :: Networking
Requires-Python: >=3.8
License-File: LICENSE
Requires-Dist: octavia-lib>=2.5.0
Requires-Dist: oslo.config>=8.0.0
Requires-Dist: oslo.log>=4.4.0
Requires-Dist: oslo.utils>=4.8.0
Requires-Dist: requests>=2.25.0
Requires-Dist: tenacity>=6.2.0
Requires-Dist: openstacksdk>=0.61.0
Provides-Extra: dev
Requires-Dist: pytest>=6.0; extra == "dev"
Requires-Dist: pytest-cov>=2.0; extra == "dev"
Requires-Dist: black>=22.0; extra == "dev"
Requires-Dist: flake8>=4.0; extra == "dev"
Requires-Dist: mypy>=0.910; extra == "dev"
Requires-Dist: pre-commit>=2.15.0; extra == "dev"
Provides-Extra: docs
Requires-Dist: sphinx>=4.0; extra == "docs"
Requires-Dist: sphinx-rtd-theme>=1.0; extra == "docs"
Dynamic: license-file
